memory_efficient_attention_pytorch/__init__.py
memory_efficient_attention_pytorch/autoregressive_wrapper.py
memory_efficient_attention_pytorch/memory_efficient_attention.py
memory_efficient_attention_pytorch/memory_efficient_cosine_sim_attention.py
memory_efficient_attention_pytorch/reversible.py
memory_efficient_attention_pytorch/transformer.py
memory_efficient_attention_pytorch-0.0.17.dist-info/LICENSE
memory_efficient_attention_pytorch-0.0.17.dist-info/METADATA
memory_efficient_attention_pytorch-0.0.17.dist-info/WHEEL
memory_efficient_attention_pytorch-0.0.17.dist-info/top_level.txt
memory_efficient_attention_pytorch-0.0.17.dist-info/RECORD
