Metadata-Version: 2.1
Name: memory-efficient-attention-pytorch
Version: 0.0.17
Summary: Memory Efficient Attention - Pytorch
Home-page: https://github.com/lucidrains/memory-efficient-attention-pytorch
Author: Phil Wang
Author-email: lucidrains@gmail.com
License: MIT
Keywords: artificial intelligence,deep learning,attention-mechanism
Platform: UNKNOWN
Classifier: Development Status :: 4 - Beta
Classifier: Intended Audience :: Developers
Classifier: Topic :: Scientific/Engineering :: Artificial Intelligence
Classifier: License :: OSI Approved :: MIT License
Classifier: Programming Language :: Python :: 3.6
License-File: LICENSE
Requires-Dist: einops (>=0.4.1)
Requires-Dist: torch (>=1.6)
